els/__init__.py
els/_typing.py
els/cli.py
els/config.py
els/core.py
els/execute.py
els/flow.py
els/path.py
els/pathprops.py
els/sa_patch.py
els/sa_utils_patch.py
elspec-0.7.4.dist-info/licenses/LICENSE
tests/__init__.py
tests/conftest.py
tests/helpers.py
tests/test_configs.py
tests/test_dtypes.py
tests/test_read_only.py
tests/test_serializer.py
tests/test_template.py
tests/test_tour.py
tests/test_tree.py
elspec-0.7.4.dist-info/METADATA
elspec-0.7.4.dist-info/WHEEL
elspec-0.7.4.dist-info/entry_points.txt
elspec-0.7.4.dist-info/top_level.txt
elspec-0.7.4.dist-info/RECORD
