Metadata-Version: 2.4
Name: elspec
Version: 0.7.4
Summary: A declarative data ingestion system
Author-email: Nathan Walsh <nwalsh82@gmail.com>
Project-URL: Homepage, https://github.com/NathanDWalsh/els
Classifier: Programming Language :: Python :: 3
Classifier: License :: OSI Approved :: MIT License
Classifier: Operating System :: OS Independent
Classifier: Development Status :: 2 - Pre-Alpha
Requires-Python: >=3.9
License-File: LICENSE
Requires-Dist: anytree>=2.12.1
Requires-Dist: duckdb-engine>=0.12.1
Requires-Dist: joblib>=1.3.2
Requires-Dist: openpyxl>=3.1.2
Requires-Dist: pandas>=2.2.3
Requires-Dist: pdfminer-six>=20231228
Requires-Dist: prqlc>=0.13.3
Requires-Dist: pydantic>=2.7.4
Requires-Dist: pymssql>=2.3.2
Requires-Dist: pyodbc>=4.0.39
Requires-Dist: python-calamine>=0.3.1
Requires-Dist: pyyaml>=6.0.1
Requires-Dist: ruamel-yaml>=0.18.6
Requires-Dist: sqlalchemy-utils>=0.41.2
Requires-Dist: sqlalchemy>=2.0.31
Requires-Dist: typer>=0.15.4
Requires-Dist: xlsxwriter>=3.2.2
Requires-Dist: azure-identity
Requires-Dist: lxml>=5.3.2
Dynamic: license-file
